odoo/addons/cooperator_somconnexio/CHANGELOG.md
odoo/addons/cooperator_somconnexio/README.rst
odoo/addons/cooperator_somconnexio/__init__.py
odoo/addons/cooperator_somconnexio/__manifest__.py
odoo/addons/cooperator_somconnexio/data/account_payment_term.xml
odoo/addons/cooperator_somconnexio/data/discovery_channel.xml
odoo/addons/cooperator_somconnexio/data/mail_activity_type.xml
odoo/addons/cooperator_somconnexio/data/operation_request_terminate_reason.xml
odoo/addons/cooperator_somconnexio/data/share_type.xml
odoo/addons/cooperator_somconnexio/demo/partner.xml
odoo/addons/cooperator_somconnexio/demo/subscription_requests.xml
odoo/addons/cooperator_somconnexio/i18n/ca_ES.po
odoo/addons/cooperator_somconnexio/i18n/es.po
odoo/addons/cooperator_somconnexio/listeners/__init__.py
odoo/addons/cooperator_somconnexio/listeners/res_partner_listener.py
odoo/addons/cooperator_somconnexio/models/__init__.py
odoo/addons/cooperator_somconnexio/models/account_move.py
odoo/addons/cooperator_somconnexio/models/contract.py
odoo/addons/cooperator_somconnexio/models/coop_agreement.py
odoo/addons/cooperator_somconnexio/models/cooperative_membership.py
odoo/addons/cooperator_somconnexio/models/crm_lead.py
odoo/addons/cooperator_somconnexio/models/crm_lead_line.py
odoo/addons/cooperator_somconnexio/models/discovery_channel.py
odoo/addons/cooperator_somconnexio/models/operation_request.py
odoo/addons/cooperator_somconnexio/models/operation_request_terminate_reason.py
odoo/addons/cooperator_somconnexio/models/partner_otrs_view.py
odoo/addons/cooperator_somconnexio/models/res_partner.py
odoo/addons/cooperator_somconnexio/models/subscription_request.py
odoo/addons/cooperator_somconnexio/reports/crm_lead_creation_CM_email_template.xml
odoo/addons/cooperator_somconnexio/reports/crm_lead_creation_email_template.xml
odoo/addons/cooperator_somconnexio/reports/crm_lead_creation_manual_email_template.xml
odoo/addons/cooperator_somconnexio/reports/sponsor_sell_back_template.xml
odoo_addon_cooperator_somconnexio-16.0.1.0.3.dist-info/METADATA
odoo_addon_cooperator_somconnexio-16.0.1.0.3.dist-info/WHEEL
odoo_addon_cooperator_somconnexio-16.0.1.0.3.dist-info/top_level.txt
odoo_addon_cooperator_somconnexio-16.0.1.0.3.dist-info/RECORD
