Metadata-Version: 2.1
Name: odoo-addon-cooperator-somconnexio
Version: 16.0.1.0.3
Summary: SomConnexio custom usage of cooperative users (cooperators).
Home-page: https://coopdevs.org
Author: Som Connexió SCCL, Coopdevs Treball SCCL
License: AGPL-3
Platform: UNKNOWN
Classifier: Programming Language :: Python
Classifier: Framework :: Odoo
Classifier: Framework :: Odoo :: 16.0
Classifier: License :: OSI Approved :: GNU Affero General Public License v3
Requires-Python: >=3.10
Requires-Dist: faker
Requires-Dist: odoo-addon-cooperator-sponsorship <16.1dev,>=16.0dev
Requires-Dist: odoo-addon-l10n-es-cooperator <16.1dev,>=16.0dev
Requires-Dist: odoo-addon-somconnexio <16.1dev,>=16.0dev
Requires-Dist: odoo <16.1dev,>=16.0a
